<?xml version="1.0" encoding="UTF-8"?>
<objects serializationModel="Studio.01.10.00">
    <object class="Event" id="{7fdf6168-22bc-4f74-85f3-f66f875af1a7}">
        <property name="name">
            <value>TowerControl</value>
        </property>
        <property name="outputFormat">
            <value>0</value>
        </property>
        <relationship name="folder">
            <destination>{0e4e096a-10d3-4955-928a-28af8b5ac59b}</destination>
        </relationship>
        <relationship name="mixer">
            <destination>{29400447-27ca-4093-ae3b-c2250e638727}</destination>
        </relationship>
        <relationship name="masterTrack">
            <destination>{bc45ca25-5aad-439d-b440-2674ccfe32db}</destination>
        </relationship>
        <relationship name="mixerInput">
            <destination>{ab481c63-5ae5-4ac0-832b-4a9757dde92b}</destination>
        </relationship>
        <relationship name="automatableProperties">
            <destination>{5ccf118d-48c1-44b9-b888-055ef6d6c2f1}</destination>
        </relationship>
        <relationship name="markerTracks">
            <destination>{2c3ca453-78ca-438d-b3e0-a0325f1473b7}</destination>
        </relationship>
        <relationship name="groupTracks">
            <destination>{ee353529-0024-4036-a17a-6d80ada6b65a}</destination>
            <destination>{847cda43-d6ed-4e21-81b2-0edbda1299f8}</destination>
            <destination>{c14e6095-e138-40a6-954e-cf87ec2110ba}</destination>
        </relationship>
        <relationship name="timeline">
            <destination>{c4202d48-296d-4f91-b5d3-ec0436443cbe}</destination>
        </relationship>
        <relationship name="parameters">
            <destination>{8995c03e-2256-4971-88f6-bbbbaaa92baa}</destination>
        </relationship>
    </object>
    <object class="EventMixer" id="{29400447-27ca-4093-ae3b-c2250e638727}">
        <relationship name="masterBus">
            <destination>{59cc921c-92c5-4386-8a38-b3f834760016}</destination>
        </relationship>
    </object>
    <object class="MasterTrack" id="{bc45ca25-5aad-439d-b440-2674ccfe32db}">
        <relationship name="mixerGroup">
            <destination>{59cc921c-92c5-4386-8a38-b3f834760016}</destination>
        </relationship>
    </object>
    <object class="MixerInput" id="{ab481c63-5ae5-4ac0-832b-4a9757dde92b}">
        <relationship name="effectChain">
            <destination>{19797033-918b-4a3e-bfe8-00a792e64bf9}</destination>
        </relationship>
        <relationship name="panner">
            <destination>{9eb53d06-5f72-419d-8c65-27909baa18a0}</destination>
        </relationship>
        <relationship name="output">
            <destination>{59e23aeb-90cb-4dbf-9f87-d3ca801c4f1d}</destination>
        </relationship>
    </object>
    <object class="EventAutomatableProperties" id="{5ccf118d-48c1-44b9-b888-055ef6d6c2f1}"/>
    <object class="MarkerTrack" id="{2c3ca453-78ca-438d-b3e0-a0325f1473b7}"/>
    <object class="GroupTrack" id="{ee353529-0024-4036-a17a-6d80ada6b65a}">
        <relationship name="modules">
            <destination>{8c40beea-5067-4488-ba74-fdb70860ed7e}</destination>
        </relationship>
        <relationship name="mixerGroup">
            <destination>{2c576bfd-edce-4b97-a194-6da9b35a897a}</destination>
        </relationship>
    </object>
    <object class="GroupTrack" id="{847cda43-d6ed-4e21-81b2-0edbda1299f8}">
        <relationship name="modules">
            <destination>{4dcdeb15-7e54-45ed-942d-d806dfd82ed3}</destination>
        </relationship>
        <relationship name="mixerGroup">
            <destination>{efd8fe8b-aba9-49b2-9fc7-b323f609e0f4}</destination>
        </relationship>
    </object>
    <object class="GroupTrack" id="{c14e6095-e138-40a6-954e-cf87ec2110ba}">
        <relationship name="modules">
            <destination>{5b7f6956-2d5b-47a6-b098-ce2a2f9939f2}</destination>
        </relationship>
        <relationship name="mixerGroup">
            <destination>{f900f74e-5a93-4086-845b-4bf03c364e0c}</destination>
        </relationship>
    </object>
    <object class="Timeline" id="{c4202d48-296d-4f91-b5d3-ec0436443cbe}"/>
    <object class="ParameterProxy" id="{8995c03e-2256-4971-88f6-bbbbaaa92baa}">
        <relationship name="modules">
            <destination>{5b7f6956-2d5b-47a6-b098-ce2a2f9939f2}</destination>
            <destination>{4dcdeb15-7e54-45ed-942d-d806dfd82ed3}</destination>
            <destination>{8c40beea-5067-4488-ba74-fdb70860ed7e}</destination>
        </relationship>
        <relationship name="preset">
            <destination>{29837784-a1eb-4811-9c22-1c3c7933118f}</destination>
        </relationship>
    </object>
    <object class="EventMixerMaster" id="{59cc921c-92c5-4386-8a38-b3f834760016}">
        <relationship name="effectChain">
            <destination>{93aa127d-44e6-4d9c-8631-0627dd595026}</destination>
        </relationship>
        <relationship name="panner">
            <destination>{becb5019-c33a-4b44-9957-5d689efc436a}</destination>
        </relationship>
        <relationship name="mixer">
            <destination>{29400447-27ca-4093-ae3b-c2250e638727}</destination>
        </relationship>
    </object>
    <object class="MixerBusEffectChain" id="{19797033-918b-4a3e-bfe8-00a792e64bf9}">
        <relationship name="effects">
            <destination>{8921942e-b7de-4822-b3a5-375fac12e8c5}</destination>
        </relationship>
    </object>
    <object class="MixerBusPanner" id="{9eb53d06-5f72-419d-8c65-27909baa18a0}"/>
    <object class="SingleSound" id="{8c40beea-5067-4488-ba74-fdb70860ed7e}">
        <property name="length">
            <value>0.10000000000000001</value>
        </property>
        <relationship name="audioFile">
            <destination>{bbe3f033-bce0-4f32-8d95-5f9b4c67a775}</destination>
        </relationship>
    </object>
    <object class="EventMixerGroup" id="{2c576bfd-edce-4b97-a194-6da9b35a897a}">
        <property name="name">
            <value>Audio 1</value>
        </property>
        <relationship name="effectChain">
            <destination>{edc4bd2d-1894-4431-b9f0-30b8de0415a7}</destination>
        </relationship>
        <relationship name="panner">
            <destination>{8ad07985-6697-434f-bb92-f1a57ead8edb}</destination>
        </relationship>
        <relationship name="output">
            <destination>{59cc921c-92c5-4386-8a38-b3f834760016}</destination>
        </relationship>
    </object>
    <object class="SingleSound" id="{4dcdeb15-7e54-45ed-942d-d806dfd82ed3}">
        <property name="start">
            <value>1</value>
        </property>
        <property name="length">
            <value>0.10000000000000001</value>
        </property>
        <relationship name="audioFile">
            <destination>{7ab3f4c8-2fcc-4cc6-b248-59f119ff2857}</destination>
        </relationship>
    </object>
    <object class="EventMixerGroup" id="{efd8fe8b-aba9-49b2-9fc7-b323f609e0f4}">
        <property name="name">
            <value>Audio 2</value>
        </property>
        <relationship name="effectChain">
            <destination>{81ca7f05-4f94-4723-b0c9-a2ecf950ddd5}</destination>
        </relationship>
        <relationship name="panner">
            <destination>{98cb9ce0-d88c-47f8-b54f-8fc69a53afaf}</destination>
        </relationship>
        <relationship name="output">
            <destination>{59cc921c-92c5-4386-8a38-b3f834760016}</destination>
        </relationship>
    </object>
    <object class="SingleSound" id="{5b7f6956-2d5b-47a6-b098-ce2a2f9939f2}">
        <property name="start">
            <value>1.9000000000000001</value>
        </property>
        <property name="length">
            <value>0.10000000000000003</value>
        </property>
        <property name="looping">
            <value>true</value>
        </property>
        <relationship name="audioFile">
            <destination>{ecde5d8d-2c36-4a49-a008-23b2fabcb3f4}</destination>
        </relationship>
    </object>
    <object class="EventMixerGroup" id="{f900f74e-5a93-4086-845b-4bf03c364e0c}">
        <property name="name">
            <value>Audio 3</value>
        </property>
        <relationship name="effectChain">
            <destination>{850daba9-0b87-46e5-817d-896175808bcb}</destination>
        </relationship>
        <relationship name="panner">
            <destination>{29f6c2e7-9fe4-49fc-b30e-09bc115ecbc9}</destination>
        </relationship>
        <relationship name="output">
            <destination>{59cc921c-92c5-4386-8a38-b3f834760016}</destination>
        </relationship>
    </object>
    <object class="MixerBusEffectChain" id="{93aa127d-44e6-4d9c-8631-0627dd595026}">
        <relationship name="effects">
            <destination>{b9385dcb-7d37-48b5-80d6-08bc630f76f1}</destination>
        </relationship>
    </object>
    <object class="MixerBusPanner" id="{becb5019-c33a-4b44-9957-5d689efc436a}"/>
    <object class="MixerBusFader" id="{8921942e-b7de-4822-b3a5-375fac12e8c5}"/>
    <object class="MixerBusEffectChain" id="{edc4bd2d-1894-4431-b9f0-30b8de0415a7}">
        <relationship name="effects">
            <destination>{380a7d4b-3097-417e-a947-6fee99c3e487}</destination>
        </relationship>
    </object>
    <object class="MixerBusPanner" id="{8ad07985-6697-434f-bb92-f1a57ead8edb}"/>
    <object class="MixerBusEffectChain" id="{81ca7f05-4f94-4723-b0c9-a2ecf950ddd5}">
        <relationship name="effects">
            <destination>{3be2f834-4d8a-47c2-ae5c-cd6ce2c791e3}</destination>
        </relationship>
    </object>
    <object class="MixerBusPanner" id="{98cb9ce0-d88c-47f8-b54f-8fc69a53afaf}"/>
    <object class="MixerBusEffectChain" id="{850daba9-0b87-46e5-817d-896175808bcb}">
        <relationship name="effects">
            <destination>{b1e168b9-ff4f-47e5-8731-47caf36af484}</destination>
        </relationship>
    </object>
    <object class="MixerBusPanner" id="{29f6c2e7-9fe4-49fc-b30e-09bc115ecbc9}"/>
    <object class="MixerBusFader" id="{b9385dcb-7d37-48b5-80d6-08bc630f76f1}"/>
    <object class="MixerBusFader" id="{380a7d4b-3097-417e-a947-6fee99c3e487}"/>
    <object class="MixerBusFader" id="{3be2f834-4d8a-47c2-ae5c-cd6ce2c791e3}"/>
    <object class="MixerBusFader" id="{b1e168b9-ff4f-47e5-8731-47caf36af484}"/>
</objects>
