<?xml version="1.0" encoding="UTF-8"?>
<objects serializationModel="Studio.01.10.00">
    <object class="Event" id="{f4e9d95d-890e-42f5-8db9-5d7fe1c962b6}">
        <property name="name">
            <value>placeholder background</value>
        </property>
        <property name="outputFormat">
            <value>1</value>
        </property>
        <relationship name="folder">
            <destination>{4739950e-bdbb-421b-afe2-96463850cff6}</destination>
        </relationship>
        <relationship name="mixer">
            <destination>{e03f81c1-08ca-4c82-8baa-a4c95bfeb811}</destination>
        </relationship>
        <relationship name="masterTrack">
            <destination>{2d02b48a-5ef3-4f80-8fed-40bf7ec9f16d}</destination>
        </relationship>
        <relationship name="mixerInput">
            <destination>{659da755-cca7-467d-8323-dcb66e1b006d}</destination>
        </relationship>
        <relationship name="automatableProperties">
            <destination>{74b64fcf-ef9b-4466-99a7-8145861f6560}</destination>
        </relationship>
        <relationship name="markerTracks">
            <destination>{9f49b9f4-7784-4c82-ad88-1e89deed8c4f}</destination>
        </relationship>
        <relationship name="groupTracks">
            <destination>{4f6c2f81-45e7-4038-ab6c-a45452e8c8b8}</destination>
        </relationship>
        <relationship name="timeline">
            <destination>{decfe948-22af-48b8-8296-e35732fb7899}</destination>
        </relationship>
        <relationship name="banks">
            <destination>{605fbaad-2991-4e92-8d95-940df6a0b35f}</destination>
        </relationship>
    </object>
    <object class="EventMixer" id="{e03f81c1-08ca-4c82-8baa-a4c95bfeb811}">
        <relationship name="masterBus">
            <destination>{1c8a5a65-5c75-4167-a498-387476de889b}</destination>
        </relationship>
    </object>
    <object class="MasterTrack" id="{2d02b48a-5ef3-4f80-8fed-40bf7ec9f16d}">
        <relationship name="mixerGroup">
            <destination>{1c8a5a65-5c75-4167-a498-387476de889b}</destination>
        </relationship>
    </object>
    <object class="MixerInput" id="{659da755-cca7-467d-8323-dcb66e1b006d}">
        <relationship name="effectChain">
            <destination>{e2118228-86f1-4aec-9c9b-452a2ab052f2}</destination>
        </relationship>
        <relationship name="panner">
            <destination>{e6003236-24ff-4d33-a9fb-ec9ba30c63bd}</destination>
        </relationship>
        <relationship name="output">
            <destination>{59e23aeb-90cb-4dbf-9f87-d3ca801c4f1d}</destination>
        </relationship>
    </object>
    <object class="EventAutomatableProperties" id="{74b64fcf-ef9b-4466-99a7-8145861f6560}"/>
    <object class="MarkerTrack" id="{9f49b9f4-7784-4c82-ad88-1e89deed8c4f}"/>
    <object class="GroupTrack" id="{4f6c2f81-45e7-4038-ab6c-a45452e8c8b8}">
        <relationship name="modules">
            <destination>{8e3947fc-6cd5-4ccc-b37e-54f0acf4796c}</destination>
        </relationship>
        <relationship name="mixerGroup">
            <destination>{1374e39e-9e38-4a7d-b18e-e97f35ada280}</destination>
        </relationship>
    </object>
    <object class="Timeline" id="{decfe948-22af-48b8-8296-e35732fb7899}">
        <relationship name="modules">
            <destination>{8e3947fc-6cd5-4ccc-b37e-54f0acf4796c}</destination>
        </relationship>
        <relationship name="markers">
            <destination>{90e463c4-7b37-4622-a6b3-25ba150e80a1}</destination>
        </relationship>
    </object>
    <object class="EventMixerMaster" id="{1c8a5a65-5c75-4167-a498-387476de889b}">
        <relationship name="effectChain">
            <destination>{af42c21a-6281-440b-abdc-f86b613ab7f0}</destination>
        </relationship>
        <relationship name="panner">
            <destination>{eff0f768-656c-47f8-9f76-b8131cfdab8a}</destination>
        </relationship>
        <relationship name="mixer">
            <destination>{e03f81c1-08ca-4c82-8baa-a4c95bfeb811}</destination>
        </relationship>
    </object>
    <object class="MixerBusEffectChain" id="{e2118228-86f1-4aec-9c9b-452a2ab052f2}">
        <relationship name="effects">
            <destination>{43f9bc23-db80-43e2-a9ad-7d48d9656790}</destination>
        </relationship>
    </object>
    <object class="MixerBusPanner" id="{e6003236-24ff-4d33-a9fb-ec9ba30c63bd}"/>
    <object class="SingleSound" id="{8e3947fc-6cd5-4ccc-b37e-54f0acf4796c}">
        <property name="length">
            <value>11.656417233560092</value>
        </property>
        <relationship name="audioFile">
            <destination>{c1738d06-3e43-4f04-86fa-f65619a53ef6}</destination>
        </relationship>
    </object>
    <object class="EventMixerGroup" id="{1374e39e-9e38-4a7d-b18e-e97f35ada280}">
        <property name="name">
            <value>Audio 1</value>
        </property>
        <relationship name="effectChain">
            <destination>{e457d27d-1a79-45cf-ba98-f7df9ca77f09}</destination>
        </relationship>
        <relationship name="panner">
            <destination>{767145ef-3e43-433c-a552-c5eaa74eada1}</destination>
        </relationship>
        <relationship name="output">
            <destination>{1c8a5a65-5c75-4167-a498-387476de889b}</destination>
        </relationship>
    </object>
    <object class="LoopRegion" id="{90e463c4-7b37-4622-a6b3-25ba150e80a1}">
        <property name="position">
            <value>0</value>
        </property>
        <property name="length">
            <value>11.4</value>
        </property>
        <relationship name="timeline">
            <destination>{decfe948-22af-48b8-8296-e35732fb7899}</destination>
        </relationship>
        <relationship name="markerTrack">
            <destination>{9f49b9f4-7784-4c82-ad88-1e89deed8c4f}</destination>
        </relationship>
    </object>
    <object class="MixerBusEffectChain" id="{af42c21a-6281-440b-abdc-f86b613ab7f0}">
        <relationship name="effects">
            <destination>{5ddf0070-9e0b-4f6a-8c95-7d4da7aa9f16}</destination>
        </relationship>
    </object>
    <object class="MixerBusPanner" id="{eff0f768-656c-47f8-9f76-b8131cfdab8a}"/>
    <object class="MixerBusFader" id="{43f9bc23-db80-43e2-a9ad-7d48d9656790}"/>
    <object class="MixerBusEffectChain" id="{e457d27d-1a79-45cf-ba98-f7df9ca77f09}">
        <relationship name="effects">
            <destination>{a8e5edff-b2ff-48a9-9310-b3d1ca15c1e2}</destination>
        </relationship>
    </object>
    <object class="MixerBusPanner" id="{767145ef-3e43-433c-a552-c5eaa74eada1}"/>
    <object class="MixerBusFader" id="{5ddf0070-9e0b-4f6a-8c95-7d4da7aa9f16}"/>
    <object class="MixerBusFader" id="{a8e5edff-b2ff-48a9-9310-b3d1ca15c1e2}"/>
</objects>
